{
    "stops": [
        {
            "id": 1,
            "name": "Cornish Road",
            "town/village": "Chipping Norton",
            "googleplaceids": [],
            "stopcodes": ["69325867"],
            "position": {
                "latitude": 51.932862,
                "longitude": -1.555381
            },
            "services": ["S3"]
        },
        {
            "id": 2,
            "name": "West Street Stop C",
            "town/village": "Chipping Norton",
            "googleplaceids": [],
            "stopcodes": ["69328362"],
            "position": {
                "latitude": 51.94023,
                "longitude": -1.546061
            },
            "services": ["S3"]
        },
        {
            "id": 3,        
            "name": "West Street Stop B",
            "town/village": "Chipping Norton",
            "googleplaceids": [],
            "stopcodes": ["69329479"],
            "position": {
                "latitude": 51.940368,
                "longitude": -1.54587
            },
            "services": ["S3"]
        },
        {
            "id": 4,        
            "name": "Enstone Green",
            "town/village": "Enstone",
            "googleplaceids": [],
            "stopcodes": ["69345236", "69345237"],
            "position": {
                "latitude": 51.915566,
                "longitude": -1.453924
            },
            "services": ["S3"]
        },
        {
            "id": 5,        
            "name": "Kiddington Turn",
            "town/village": "A44",
            "googleplaceids": [],
            "stopcodes": ["69327539", "69327538"],
            "position": {
                "latitude": 51.896089,
                "longitude": -1.406465
            },
            "services": ["S3"]
        },        
        {
            "id": 6,        
            "name": "Village Shops",
            "town/village": "Chadlington",
            "googleplaceids": [],
            "stopcodes": ["69345354", "69345367"],
            "position": {
                "latitude": 51.895649,
                "longitude": -1.525265
            },
            "services": ["S3"]
        },
        {
            "id": 7,        
            "name": "Spelsbury Green",
            "town/village": "Spelsbury",
            "googleplaceids": [],
            "stopcodes": ["69327938", "69327939"],
            "position": {
                "latitude": 51.893901,
                "longitude": -1.494237
            },
            "services": ["S3"]
        },
        {
            "id": 8,        
            "name": "The Bell Hotel",
            "town/village": "Charlbury",
            "googleplaceids": [],
            "stopcodes": ["69326756"],
            "position": {
                "latitude": 51.872291,
                "longitude": -1.483262
            },
            "services": ["S3"]
        },
        {
            "id": 9,        
            "name": "Main Street",
            "town/village": "Fawler",
            "googleplaceids": [],
            "stopcodes": ["69342725", "69326275"],
            "position": {
                "latitude": 51.850929,
                "longitude": -1.461631
            },
            "services": ["S3"]
        }, 
        {
            "id": 10,        
            "name": "Wychwood Close",
            "town/village": "Charlbury",
            "googleplaceids": [],
            "stopcodes": ["69345647"],
            "position": {
                "latitude": 51.87457,
                "longitude": -1.476806
            },
            "services": ["S3"]
        }, 
        {
            "id": 11,        
            "name": "Prospect Close",
            "town/village": "Stonesfield",
            "googleplaceids": [],
            "stopcodes": ["69342735", "69327235"],
            "position": {
                "latitude": 51.851901,
                "longitude": -1.428024
            },
            "services": ["S3"]
        },    
        {
            "id": 12,        
            "name": "Akeman Street",
            "town/village": "Combe",
            "googleplaceids": [],
            "stopcodes": ["69342737", "69325879"],
            "position": {
                "latitude": 51.843272,
                "longitude": -1.403461
            },
            "services": ["S3"]
        },   
        {
            "id": 13,        
            "name": "Hill Rise",
            "town/village": "Old Woodstock",
            "googleplaceids": [],
            "stopcodes": ["69329593", "69329592"],
            "position": {
                "latitude": 51.855516,
                "longitude": -1.36179
            },
            "services": ["S3"]
        },   
        {
            "id": 14,        
            "name": "Vermont Drive",
            "town/village": "Old Woodstock",
            "googleplaceids": [],
            "stopcodes": ["69327983"],
            "position": {
                "latitude": 51.853538,
                "longitude": -1.360336
            },
            "services": ["S3"]
        },
        {
            "id": 15,        
            "name": "Marlborough Grill",
            "town/village": "Woodstock",
            "googleplaceids": [],
            "stopcodes": ["69343976", "69343982"],
            "position": {
                "latitude": 51.847451,
                "longitude": -1.353845
            },
            "services": ["S3"]
        }, 
        {
            "id": 16,        
            "name": "Blenheim Palace",
            "town/village": "Woodstock",
            "googleplaceids": [],
            "stopcodes": ["69323856", "69323854"],
            "position": {
                "latitude": 51.845585,
                "longitude": -1.350288
            },
            "services": ["S3"]
        },     
        {
            "id": 17,        
            "name": "The Royal Sun",
            "town/village": "Begbroke",
            "googleplaceids": [],
            "stopcodes": ["69343725", "69343726"],
            "position": {
                "latitude": 51.822026,
                "longitude": -1.318976
            },
            "services": ["S3"]
        },  
        {
            "id": 18,        
            "name": "Enstone Road",
            "town/village": "Charlbury",
            "googleplaceids": [],
            "stopcodes": ["69327364"],
            "position": {
                "latitude": 51.875574,
                "longitude": -1.478627
            },
            "services": ["S3"]
        },
        {
            "id": 19,        
            "name": "Dancers Hill",
            "town/village": "Charlbury",
            "googleplaceids": [],
            "stopcodes": ["69347454"],
            "position": {
                "latitude": 51.870589,
                "longitude": -1.476556
            },
            "services": ["S3"]
        },  
        {
            "id": 20,        
            "name": "George Street Stop A5",
            "town/village": "Oxford City Centre",
            "googleplaceids": [],
            "stopcodes": ["69327525"],
            "position": {
                "latitude": 51.753452,
                "longitude": -1.26253
            },
            "services": ["S3"]
        }, 
        {
            "id": 21,        
            "name": "Gloucester Green Bus Station Bay 8",
            "town/village": "Oxford City Centre",
            "googleplaceids": [],
            "stopcodes": ["69326495"],
            "position": {
                "latitude": 51.754042,
                "longitude": -1.262497
            },
            "services": ["S1", "S3"]
        },
        {
            "id": 22,        
            "name": "Oxford Rail Stn Stop R5",
            "town/village": "Oxford City Centre",
            "googleplaceids": [],
            "stopcodes": ["69326562"],
            "position": {
                "latitude": 51.753426,
                "longitude": -1.269511
            },
            "services": ["S3"]
        },
        {
            "id": 23,        
            "name": "Pear Tree P&R Car Park",
            "town/village": "Pear Tree",
            "googleplaceids": [],
            "stopcodes": ["69327697"],
            "position": {
                "latitude": 51.793336,
                "longitude": -1.28202
            },
            "services": ["300"]
        },
        {
            "id": 24,        
            "name": "Sawmill",
            "town/village": "Bagley Wood",
            "googleplaceids": [],
            "stopcodes": ["69324725", "69324724"],
            "position": {
                "latitude": 51.714031,
                "longitude": -1.265799
            },
            "services": ["300"]
        },
        {
            "id": 25,        
            "name": "Redbridge P&R Car Park",
            "town/village": "Redbridge",
            "googleplaceids": [],
            "stopcodes": ["69327698"],
            "position": {
                "latitude": 51.729853,
                "longitude": -1.249233
            },
            "services": ["300"]
        },
        {
            "id": 26,        
            "name": "Magdalen Street Stop C2",
            "town/village": "Oxford City Centre",
            "googleplaceids": [],
            "stopcodes": ["69326486"],
            "position": {
                "latitude": 51.754581,
                "longitude": -1.25918
            },
            "services": ["300"]
        },
        {
            "id": 27,        
            "name": "Water Eaton Park & Ride",
            "town/village": "Water Eaton",
            "googleplaceids": [],
            "stopcodes": ["69345359","69345357"],
            "position": {
                "latitude": 51.802819,
                "longitude": -1.273029
            },
            "services": ["2", "2A", "2B", "S5"]
        }, 
        {
            "id": 28,        
            "name": "Water Eaton Terminal",
            "town/village": "Water Eaton",
            "googleplaceids": [],
            "stopcodes": ["69328763"],
            "position": {
                "latitude": 51.802819,
                "longitude": -1.273029
            },
            "services": []
        },
        {
            "id": 29,        
            "name": "George Street Stop A3",
            "town/village": "Oxford City Centre",
            "googleplaceids": [],
            "stopcodes": ["69327485"],
            "position": {
                "latitude": 51.753452,
                "longitude": -1.26253
            },
            "services": ["S1"]
        },
        {
            "id": 30,        
            "name": "Elms Parade Shops",
            "town/village": "Botley",
            "googleplaceids": [],
            "stopcodes": ["69323497", "69323498"],
            "position": {
                "latitude": 51.75165,
                "longitude": -1.298318
            },
            "services": ["S1", "4A", "4", "X30", "X31"]
        },
        {
            "id": 31,        
            "name": "Eynsham Church",
            "town/village": "Eynsham",
            "googleplaceids": [],
            "stopcodes": ["69327535", "69328424"],
            "position": {
                "latitude": 51.780387,
                "longitude": -1.372916
            },
            "services": ["S1"]
        },
        {
            "id": 32,        
            "name": "Market Square Stop A",
            "town/village": "Witney",
            "googleplaceids": [],
            "stopcodes": ["69327463"],
            "position": {
                "latitude": 51.783924,
                "longitude": -1.485371
            },
            "services": ["S1"]
        },
        {
            "id": 33,        
            "name": "Bartholomew School",
            "town/village": "Eynsham",
            "googleplaceids": [],
            "stopcodes": ["69346597", "69346596"],
            "position": {
                "latitude": 51.782252,
                "longitude": -1.381413
            },
            "services": ["S1"]
        },
        {
            "id": 34,        
            "name": "Market Square Stop D",
            "town/village": "Witney",
            "googleplaceids": [],
            "stopcodes": ["69328497"],
            "position": {
                "latitude": 51.784077,
                "longitude": -1.485601
            },
            "services": ["S1"]
        },
        {
            "id": 35,        
            "name": "Bus Garage",
            "town/village": "Witney",
            "googleplaceids": [],
            "stopcodes": ["69327347", "69327348"],
            "position": {
                "latitude": 51.785,
                "longitude": -1.494194
            },
            "services": ["S1"]
        },
        {
            "id": 36,        
            "name": "Thorney Leys",
            "town/village": "Witney",
            "googleplaceids": [],
            "stopcodes": ["69326983", "69326984"],
            "position": {
                "latitude": 51.780128,
                "longitude": -1.509676
            },
            "services": ["S1"]
        },
        {
            "id": 37,        
            "name": "Well Lane",
            "town/village": "Curbridge",
            "googleplaceids": [],
            "stopcodes": ["69323956", "69323954"],
            "position": {
                "latitude": 51.77736,
                "longitude": -1.522808
            },
            "services": ["S1"]
        },
        {
            "id": 38,        
            "name": "Crossroads",
            "town/village": "Carterton",
            "googleplaceids": [],
            "stopcodes": ["69326749"],
            "position": {
                "latitude": 51.75952,
                "longitude": -1.593608
            },
            "services": ["S1", "S2"]
        },
        {
            "id": 39,        
            "name": "Bovingdon Road",
            "town/village": "Carterton",
            "googleplaceids": [],
            "stopcodes": ["69327328"],
            "position": {
                "latitude": 51.763385,
                "longitude": -1.587267
            },
            "services": ["S1", "S2"]
        },
        {
            "id": 40,        
            "name": "Broadshires Health Centre",
            "town/village": "Carterton",
            "googleplaceids": [],
            "stopcodes": ["69326923", "69326898"],
            "position": {
                "latitude": 51.764633,
                "longitude": -1.586902
            },
            "services": ["S1", "S2"]
        },
        {
            "id": 41,        
            "name": "Brize Norton Roundabout",
            "town/village": "Brize Norton",
            "googleplaceids": [],
            "stopcodes": ["69347365", "69347364"],
            "position": {
                "latitude": 51.764633,
                "longitude": -1.586902
            },
            "services": ["S1", "S2"]
        },
        {
            "id": 42,        
            "name": "Edward Stone Rise",
            "town/village": "Chipping Norton",
            "googleplaceids": [],
            "stopcodes": ["69345839"],
            "position": {
                "latitude": 51.936242,
                "longitude": -1.54889
            },
            "services": ["S3"]
        },
        {
            "id": 43,        
            "name": "Churchill House",
            "town/village": "Chipping Norton",
            "googleplaceids": [],
            "stopcodes": ["69345827"],
            "position": {
                "latitude": 51.934211,
                "longitude": -1.552581
            },
            "services": ["S3"]
        },
        {
            "id": 44,        
            "name": "Playing Field",
            "town/village": "Chipping Norton",
            "googleplaceids": [],
            "stopcodes": ["69347462"],
            "position": {
                "latitude": 51.93264,
                "longitude": -1.552068
            },
            "services": ["S3"]
        },
        {
            "id": 45,        
            "name": "Hailey Road",
            "town/village": "Chipping Norton",
            "googleplaceids": [],
            "stopcodes": ["69346352"],
            "position": {
                "latitude": 51.933404,
                "longitude": -1.549791
            },
            "services": ["S3"]
        },
        {
            "id": 46,        
            "name": "Walterbrush Road",
            "town/village": "Chipping Norton",
            "googleplaceids": [],
            "stopcodes": ["69345852"],
            "position": {
                "latitude": 51.934998,
                "longitude": -1.547195
            },
            "services": ["S3"]
        },
        {
            "id": 47,        
            "name": "Police Station",
            "town/village": "Chipping Norton",
            "googleplaceids": [],
            "stopcodes": ["69329398", "69329397"],
            "position": {
                "latitude": 51.943911,
                "longitude": -1.54168
            },
            "services": ["S3"]
        },
        {
            "id": 48,        
            "name": "Trinity Road",
            "town/village": "Chipping Norton",
            "googleplaceids": [],
            "stopcodes": ["69347293", "69347294"],
            "position": {
                "latitude": 51.944152,
                "longitude": -1.535189
            },
            "services": ["S3"]
        },
        {
            "id": 49,        
            "name": "Chipping Norton School",
            "town/village": "Chipping Norton",
            "googleplaceids": [],
            "stopcodes": ["69347896", "69347897"],
            "position": {
                "latitude": 51.936424,
                "longitude": -1.543547
            },
            "services": ["S3"]
        },
        {
            "id": 50,        
            "name": "The Beeches",
            "town/village": "Chipping Norton",
            "googleplaceids": [],
            "stopcodes": ["69348465", "69348464"],
            "position": {
                "latitude": 51.921462,
                "longitude": -1.542034
            },
            "services": ["S3"]
        },
        {
            "id": 51,        
            "name": "Farm End",
            "town/village": "Old Woodstock",
            "googleplaceids": [],
            "stopcodes": ["69343974", "69343962"],
            "position": {
                "latitude": 51.852309,
                "longitude": -1.361023
            },
            "services": ["S3"]
        },
        {
            "id": 52,        
            "name": "Roundabout",
            "town/village": "Bladon",
            "googleplaceids": [],
            "stopcodes": ["69327393", "69327436"],
            "position": {
                "latitude": 51.837203,
                "longitude": -1.334774
            },
            "services": ["S3"]
        },
        {
            "id": 53,        
            "name": "Langford Lane",
            "town/village": "Begbroke",
            "googleplaceids": [],
            "stopcodes": ["69343984", "69343983"],
            "position": {
                "latitude": 51.828193,
                "longitude": -1.322351
            },
            "services": ["S3"]
        },
        {
            "id": 54,        
            "name": "Sandy Lane",
            "town/village": "Yarnton",
            "googleplaceids": [],
            "stopcodes": ["69329589", "69329587"],
            "position": {
                "latitude": 51.814505,
                "longitude": -1.314068
            },
            "services": ["S3"]
        },
        {
            "id": 55,        
            "name": "Aysgarth Road",
            "town/village": "Yarnton",
            "googleplaceids": [],
            "stopcodes": ["69343724", "69343723"],
            "position": {
                "latitude": 51.811016,
                "longitude": -1.312732
            },
            "services": ["S3"]
        },
        {
            "id": 56,        
            "name": "The Garth",
            "town/village": "Yarnton",
            "googleplaceids": [],
            "stopcodes": ["69347292"],
            "position": {
                "latitude": 51.809285,
                "longitude": -1.312357
            },
            "services": ["S3"]
        },
        {
            "id": 57,        
            "name": "William Fletcher School",
            "town/village": "Yarnton",
            "googleplaceids": [],
            "stopcodes": ["69343698", "69343697"],
            "position": {
                "latitude": 51.807623,
                "longitude": -1.312019
            },
            "services": ["S3"]
        },
        {
            "id": 58,        
            "name": "The Paddocks",
            "town/village": "Yarnton",
            "googleplaceids": [],
            "stopcodes": ["69345286", "69345267"],
            "position": {
                "latitude": 51.805593,
                "longitude": -1.310243
            },
            "services": ["S3"]
        },
        {
            "id": 59,        
            "name": "Great Close Road",
            "town/village": "Yarnton",
            "googleplaceids": [],
            "stopcodes": ["69345293", "69345287"],
            "position": {
                "latitude": 51.805902,
                "longitude": -1.30166
            },
            "services": ["S3"]
        },
        {
            "id": 60,        
            "name": "A44",
            "town/village": "Pear Tree",
            "googleplaceids": [],
            "stopcodes": ["69329585", "69329567"],
            "position": {
                "latitude": 51.792174,
                "longitude": -1.283791
            },
            "services": ["S3"]
        },
        {
            "id": 61,        
            "name": "Wolvercote Roundabout",
            "town/village": "Woodstock Road",
            "googleplaceids": [],
            "stopcodes": ["69323935"],
            "position": {
                "latitude": 51.787369,
                "longitude": -1.279703
            },
            "services": ["S3"]
        },
        {
            "id": 62,        
            "name": "First Turn",
            "town/village": "Woodstock Road",
            "googleplaceids": [],
            "stopcodes": ["69323789", "69323787"],
            "position": {
                "latitude": 51.785713,
                "longitude": -1.278282
            },
            "services": ["S3"]
        },
        {
            "id": 63,        
            "name": "Woodstock Close",
            "town/village": "Woodstock Road",
            "googleplaceids": [],
            "stopcodes": ["69323786", "69323785"],
            "position": {
                "latitude": 51.783862,
                "longitude": -1.275761
            },
            "services": ["S3"]
        },
        {
            "id": 64,        
            "name": "Squitchey Lane",
            "town/village": "Woodstock Road",
            "googleplaceids": [],
            "stopcodes": ["69323783", "69323754"],
            "position": {
                "latitude": 51.781774,
                "longitude": -1.272864
            },
            "services": ["S3"]
        },
        {
            "id": 65,        
            "name": "Osberton Road",
            "town/village": "Woodstock Road",
            "googleplaceids": [],
            "stopcodes": ["69323769", "69323823"],
            "position": {
                "latitude": 51.778668,
                "longitude": -1.271281
            },
            "services": ["S3"]
        },
        {
            "id": 66,        
            "name": "South Parade",
            "town/village": "Woodstock Road",
            "googleplaceids": [],
            "stopcodes": ["69323768", "69323767"],
            "position": {
                "latitude": 51.777071,
                "longitude": -1.269833
            },
            "services": ["S3"]
        },
        {
            "id": 67,        
            "name": "Beechcroft Road",
            "town/village": "Woodstock Road",
            "googleplaceids": [],
            "stopcodes": ["69323765", "69323764"],
            "position": {
                "latitude": 51.774373,
                "longitude": -1.267714
            },
            "services": ["S3"]
        },
        {
            "id": 68,        
            "name": "Lathbury Road",
            "town/village": "Woodstock Road",
            "googleplaceids": [],
            "stopcodes": ["69323763", "69323762"],
            "position": {
                "latitude": 51.771302,
                "longitude": -1.266791
            },
            "services": ["S3"]
        },
        {
            "id": 69,        
            "name": "St Margaret's Road",
            "town/village": "Woodstock Road",
            "googleplaceids": [],
            "stopcodes": ["69323759", "69323758"],
            "position": {
                "latitude": 51.767847,
                "longitude": -1.265633
            },
            "services": ["S3"]
        },
        {
            "id": 70,        
            "name": "Canterbury Road",
            "town/village": "Woodstock Road",
            "googleplaceids": [],
            "stopcodes": ["69323757", "69323756"],
            "position": {
                "latitude": 51.765473,
                "longitude": -1.264967
            },
            "services": ["S3"]
        },
        {
            "id": 71,        
            "name": "Plantation Road",
            "town/village": "Woodstock Road",
            "googleplaceids": [],
            "stopcodes": ["69323843", "69323839"],
            "position": {
                "latitude": 51.763305,
                "longitude": -1.263787
            },
            "services": ["S3"]
        },
        {
            "id": 72,        
            "name": "Radcliffe Infirmary",
            "town/village": "Woodstock Road",
            "googleplaceids": [],
            "stopcodes": ["69323784", "69323858"],
            "position": {
                "latitude": 51.760486,
                "longitude": -1.261716
            },
            "services": ["S3"]
        },
        {
            "id": 73,        
            "name": "George Street Stop A1",
            "town/village": "Oxford City Centre",
            "googleplaceids": [],
            "stopcodes": ["69327528"],
            "position": {
                "latitude": 51.753792,
                "longitude": -1.259549
            },
            "services": ["S3"]
        },
        {
            "id": 74,        
            "name": "George Street Stop B2",
            "town/village": "Oxford City Centre",
            "googleplaceids": [],
            "stopcodes": ["69327523"],
            "position": {
                "latitude": 51.753941,
                "longitude": -1.259292
            },
            "services": ["S3"]
        },
        {
            "id": 75,        
            "name": "Park End St Stop E7",
            "town/village": "Oxford City Centre",
            "googleplaceids": [],
            "stopcodes": ["69327497"],
            "position": {
                "latitude": 51.752726,
                "longitude": -1.265096
            },
            "services": ["S3"]
        },
        {
            "id": 76,        
            "name": "Frideswide Square Stop R8",
            "town/village": "Oxford City Centre",
            "googleplaceids": [],
            "stopcodes": ["69328968"],
            "position": {
                "latitude": 51.752766,
                "longitude": -1.267875
            },
            "services": ["S1", "280", "U1"]
        },
        {
            "id": 77,        
            "name": "Duke of Marlborough",
            "town/village": "A44",
            "googleplaceids": [],
            "stopcodes": ["69345276", "69343964"],
            "position": {
                "latitude": 51.869029,
                "longitude": -1.377824
            },
            "services": ["S3"]
        },
        {
            "id": 78,        
            "name": "Stonesfield Road",
            "town/village": "Combe",
            "googleplaceids": [],
            "stopcodes": ["69329595", "69329594"],
            "position": {
                "latitude": 51.843308,
                "longitude": -1.405955
            },
            "services": ["S3"]
        },
        {
            "id": 79,        
            "name": "Boot Street",
            "town/village": "Stonesfield",
            "googleplaceids": [],
            "stopcodes": ["69342724", "69342723"],
            "position": {
                "latitude": 51.853571,
                "longitude": -1.43238
            },
            "services": ["S3"]
        },
        {
            "id": 80,        
            "name": "Stonesfield Green",
            "town/village": "Stonesfield",
            "googleplaceids": [],
            "stopcodes": ["69342698", "69342784"],
            "position": {
                "latitude": 51.854986,
                "longitude": -1.43069
            },
            "services": ["S3"]
        },
        {
            "id": 81,        
            "name": "Combe Road",
            "town/village": "Stonesfield",
            "googleplaceids": [],
            "stopcodes": ["69347383", "69347384"],
            "position": {
                "latitude": 51.850473,
                "longitude": -1.424907
            },
            "services": ["S3"]
        },
        {
            "id": 82,        
            "name": "Nine Acres Lane",
            "town/village": "Charlbury",
            "googleplaceids": [],
            "stopcodes": ["69327362", "69327359"],
            "position": {
                "latitude": 51.875444,
                "longitude": -1.483347
            },
            "services": ["S3"]
        },
        {
            "id": 83,        
            "name": "Crossroads",
            "town/village": "Charlbury",
            "googleplaceids": [],
            "stopcodes": ["69347458"],
            "position": {
                "latitude": 51.875776,
                "longitude": -1.479024
            },
            "services": ["S3"]
        },
        {
            "id": 84,        
            "name": "Sturt Close",
            "town/village": "Charlbury",
            "googleplaceids": [],
            "stopcodes": ["69327363"],
            "position": {
                "latitude": 51.867721,
                "longitude": -1.477522
            },
            "services": ["S3"]
        },
        {
            "id": 85,        
            "name": "Fiveways",
            "town/village": "Charlbury",
            "googleplaceids": [],
            "stopcodes": ["69345643"],
            "position": {
                "latitude": 51.86682,
                "longitude": -1.478702
            },
            "services": ["S3"]
        },
        {
            "id": 86,        
            "name": "Spendlove Centre",
            "town/village": "Charlbury",
            "googleplaceids": [],
            "stopcodes": ["69345489"],
            "position": {
                "latitude": 51.873679,
                "longitude": -1.481132
            },
            "services": ["S3"]
        },
        {
            "id": 87,        
            "name": "Caravan Park",
            "town/village": "Chadlington",
            "googleplaceids": [],
            "stopcodes": ["69348486", "69348467"],
            "position": {
                "latitude": 51.917101,
                "longitude": -1.541787
            },
            "services": ["S3"]
        },
        {
            "id": 88,        
            "name": "Chipping Norton Road",
            "town/village": "Chadlington",
            "googleplaceids": [],
            "stopcodes": ["69342728", "69342729"],
            "position": {
                "latitude": 51.900568,
                "longitude": -1.527658
            },
            "services": ["S3"]
        },
        {
            "id": 89,        
            "name": "Church Road",
            "town/village": "Chadlington",
            "googleplaceids": [],
            "stopcodes": ["69342726", "69342727"],
            "position": {
                "latitude": 51.898866,
                "longitude": -1.526724
            },
            "services": ["S3"]
        },
        {
            "id": 90,        
            "name": "Auburn House",
            "town/village": "Chadlington",
            "googleplaceids": [],
            "stopcodes": ["69323495", "69323536"],
            "position": {
                "latitude": 51.895126,
                "longitude": -1.521649
            },
            "services": ["S3"]
        },
        {
            "id": 91,        
            "name": "Spelsbury Church",
            "town/village": "Spelsbury",
            "googleplaceids": [],
            "stopcodes": ["69329596", "69329597"],
            "position": {
                "latitude": 51.892517,
                "longitude": -1.493014
            },
            "services": ["S3"]
        },
        {
            "id": 92,        
            "name": "St Nicholas Church",
            "town/village": "Spelsbury",
            "googleplaceids": [],
            "stopcodes": ["69348532", "69348529"],
            "position": {
                "latitude": 51.896046,
                "longitude": -1.516221
            },
            "services": ["S3"]
        },
        {
            "id": 93,        
            "name": "Glympton Turn",
            "town/village": "A44",
            "googleplaceids": [],
            "stopcodes": ["69347263", "69347262"],
            "position": {
                "latitude": 51.882154,
                "longitude": -1.388891
            },
            "services": ["S3"]
        },
        {
            "id": 94,        
            "name": "Worths Garage",
            "town/village": "Enstone",
            "googleplaceids": [],
            "stopcodes": ["69345646", "69345645"],
            "position": {
                "latitude": 51.912145,
                "longitude": -1.448007
            },
            "services": ["S3"]
        },
        {
            "id": 95,        
            "name": "The Harrow",
            "town/village": "Enstone",
            "googleplaceids": [],
            "stopcodes": ["69345234", "69345235"],
            "position": {
                "latitude": 51.917571,
                "longitude": -1.454927
            },
            "services": ["S3"]
        },
        {
            "id": 96,        
            "name": "Enstone Green",
            "town/village": "Enstone",
            "googleplaceids": [],
            "stopcodes": ["69345237", "69345236"],
            "position": {
                "latitude": 51.915758,
                "longitude": -1.453875
            },
            "services": ["S3"]
        },
        {
            "id": 97,        
            "name": "London Road",
            "town/village": "A44",
            "googleplaceids": [],
            "stopcodes": ["69345437", "69345435"],
            "position": {
                "latitude": 51.94236,
                "longitude": -1.513968
            },
            "services": ["S3"]
        },
        {
            "id": 98,        
            "name": "Chalford Oaks",
            "town/village": "A44",
            "googleplaceids": [],
            "stopcodes": ["69347572", "69347569"],
            "position": {
                "latitude": 51.93818,
                "longitude": -1.504548
            },
            "services": ["S3"]
        },
        {
            "id": 99,        
            "name": "Lidstone Turn",
            "town/village": "A44",
            "googleplaceids": [],
            "stopcodes": ["69343989", "69345232"],
            "position": {
                "latitude": 51.926041,
                "longitude": -1.482038
            },
            "services": ["S3"]
        },
        {
            "id": 100,        
            "name": "Market Place Stop B",
            "town/village": "Wantage",
            "googleplaceids": [],
            "stopcodes": ["69326896"],
            "position": {
                "latitude": 51.588563,
                "longitude": -1.427037
            },
            "services": ["1", "X30", "31"]
        },
        {
            "id": 101,        
            "name": "Market Place Stop A",
            "town/village": "Wantage",
            "googleplaceids": [],
            "stopcodes": ["69326895"],
            "position": {
                "latitude": 51.588486,
                "longitude": -1.426758
            },
            "services": []
        },
        {
            "id": 102,        
            "name": "Seesen Way",
            "town/village": "Wantage",
            "googleplaceids": [],
            "stopcodes": ["69328372", "69328369"],
            "position": {
                "latitude": 51.58922,
                "longitude": -1.423105
            },
            "services": ["1", "X30", "31"]
        },
        {
            "id": 103,        
            "name": "Humber Close",
            "town/village": "Wantage",
            "googleplaceids": [],
            "stopcodes": ["69328373", "69328396"],
            "position": {
                "latitude": 51.591379,
                "longitude": -1.423695
            },
            "services": ["1", "X30", "31"]
        },
        {
            "id": 104,        
            "name": "Harcourt Way",
            "town/village": "Wantage",
            "googleplaceids": [],
            "stopcodes": ["69328376", "69328358"],
            "position": {
                "latitude": 51.594598,
                "longitude": -1.422783
            },
            "services": ["1", "X30", "31"]
        },
        {
            "id": 105,        
            "name": "Grove Road Rbt",
            "town/village": "Wantage",
            "googleplaceids": [],
            "stopcodes": ["69328379", "69328382"],
            "position": {
                "latitude": 51.597848,
                "longitude": -1.422526
            },
            "services": ["1", "X30", "31"]
        },
        {
            "id": 106,        
            "name": "Wolage Drive",
            "town/village": "Grove",
            "googleplaceids": [],
            "stopcodes": ["69347867"],
            "position": {
                "latitude": 51.599317,
                "longitude": -1.422805
            },
            "services": ["1", "X30", "31"]
        },
        {
            "id": 107,        
            "name": "Mandhill Close",
            "town/village": "Grove",
            "googleplaceids": [],
            "stopcodes": ["69345257", "69345269"],
            "position": {
                "latitude": 51.603792,
                "longitude": -1.421989
            },
            "services": ["1", "X30", "31"]
        },
        {
            "id": 108,        
            "name": "Bosleys Orchard",
            "town/village": "Grove",
            "googleplaceids": [],
            "stopcodes": ["69324386", "69324385"],
            "position": {
                "latitude": 51.607214,
                "longitude": -1.421775
            },
            "services": ["1", "X30", "31"]
        },
        {
            "id": 109,        
            "name": "Millbrook Square",
            "town/village": "Grove",
            "googleplaceids": [],
            "stopcodes": ["69324383", "69324384"],
            "position": {
                "latitude": 51.609849,
                "longitude": -1.421549
            },
            "services": ["1", "X30", "31"]
        },
        {
            "id": 110,        
            "name": "Grove Green",
            "town/village": "Grove",
            "googleplaceids": [],
            "stopcodes": ["69325946", "69328383"],
            "position": {
                "latitude": 51.611744,
                "longitude": -1.420691
            },
            "services": ["1", "X30", "31"]
        },
        {
            "id": 111,        
            "name": "Mayfield Avenue",
            "town/village": "Grove",
            "googleplaceids": [],
            "stopcodes": ["69323828", "69323829"],
            "position": {
                "latitude": 51.611831,
                "longitude": -1.415493
            },
            "services": ["1", "X30", "31"]
        },
        {
            "id": 112,        
            "name": "Williams Rbt",
            "town/village": "Grove",
            "googleplaceids": [],
            "stopcodes": ["69347656", "69347386"],
            "position": {
                "latitude": 51.617031,
                "longitude": -1.410397
            },
            "services": ["1", "X30", "31"]
        },
        {
            "id": 113,        
            "name": "Ashfields Lane",
            "town/village": "East Hanney",
            "googleplaceids": [],
            "stopcodes": ["69324262", "69324259"],
            "position": {
                "latitude": 51.636808,
                "longitude": -1.392388
            },
            "services": ["1", "X30", "31"]
        },
        {
            "id": 114,        
            "name": "The Mulberries",
            "town/village": "East Hanney",
            "googleplaceids": [],
            "stopcodes": ["69347256", "69347257"],
            "position": {
                "latitude": 51.631308,
                "longitude": -1.401889
            },
            "services": ["1", "X30", "31"]
        },
        {
            "id": 115,        
            "name": "Black Horse",
            "town/village": "East Hanney",
            "googleplaceids": [],
            "stopcodes": ["69325785", "69328368"],
            "position": {
                "latitude": 51.632636,
                "longitude": -1.399646
            },
            "services": ["1", "X30", "31"]
        },
        {
            "id": 116,        
            "name": "St James View",
            "town/village": "East Hanney",
            "googleplaceids": [],
            "stopcodes": ["69329683", "69325754"],
            "position": {
                "latitude": 51.634328,
                "longitude": -1.396374
            },
            "services": ["1", "X30", "31"]
        },
        {
            "id": 117,        
            "name": "Hinksey Hill Top",
            "town/village": "Abingdon Road",
            "googleplaceids": [],
            "stopcodes": ["69323685", "69323958"],
            "position": {
                "latitude": 51.722339,
                "longitude": -1.268073
            },
            "services": ["X30", "31"]
        },
        {
            "id": 118,        
            "name": "Hinksey Hill Bottom",
            "town/village": "Abingdon Road",
            "googleplaceids": [],
            "stopcodes": ["69323683", "69323682"],
            "position": {
                "latitude": 51.726553,
                "longitude": -1.26184
            },
            "services": ["X30", "31"]
        },
        {
            "id": 119,        
            "name": "Redbridge Bertie Place",
            "town/village": "Abingdon Road",
            "googleplaceids": [],
            "stopcodes": ["69324637"],
            "position": {
                "latitude": 51.731427,
                "longitude": -1.250086
            },
            "services": ["X30", "31"]
        },
        {
            "id": 120,        
            "name": "Canning Crescent",
            "town/village": "Abingdon Road",
            "googleplaceids": [],
            "stopcodes": ["69324972", "69325265"],
            "position": {
                "latitude": 51.73275,
                "longitude": -1.249174
            },
            "services": ["X30", "31"]
        },
        {
            "id": 121,        
            "name": "Chatham Road",
            "town/village": "Abingdon Road",
            "googleplaceids": [],
            "stopcodes": ["69323792", "69323793"],
            "position": {
                "latitude": 51.735062,
                "longitude": -1.250612
            },
            "services": ["X30", "31"]
        },
        {
            "id": 122,        
            "name": "Lincoln Road",
            "town/village": "Abingdon Road",
            "googleplaceids": [],
            "stopcodes": ["69323795", "69323794"],
            "position": {
                "latitude": 51.737045,
                "longitude": -1.251765
            },
            "services": ["X30", "31"]
        },
        {
            "id": 123,        
            "name": "Lake Street",
            "town/village": "Abingdon Road",
            "googleplaceids": [],
            "stopcodes": ["69323797", "69323796"],
            "position": {
                "latitude": 51.740155,
                "longitude": -1.253879
            },
            "services": ["X30", "31"]
        },
        {
            "id": 124,        
            "name": "Newton Road",
            "town/village": "Abingdon Road",
            "googleplaceids": [],
            "stopcodes": ["69323782", "69323879"],
            "position": {
                "latitude": 51.742098,
                "longitude": -1.255118
            },
            "services": ["X30", "31"]
        },
        {
            "id": 125,        
            "name": "Whitehouse Road",
            "town/village": "Abingdon Road",
            "googleplaceids": [],
            "stopcodes": ["69323859", "69323934"],
            "position": {
                "latitude": 51.744084,
                "longitude": -1.255982
            },
            "services": ["X30", "31"]
        },
        {
            "id": 126,        
            "name": "New Road Stop D3",
            "town/village": "Oxford City Centre",
            "googleplaceids": [],
            "stopcodes": ["69327494"],
            "position": {
                "latitude": 51.75236,
                "longitude": -1.262344
            },
            "services": ["X30", "31"]
        },
        {
            "id": 127,        
            "name": "Garford Turn",
            "town/village": "Garford",
            "googleplaceids": [],
            "stopcodes": ["69324347", "69324346"],
            "position": {
                "latitude": 51.660038,
                "longitude": -1.372079
            },
            "services": ["X30", "31"]
        },
        {
            "id": 128,        
            "name": "Minns Ind. Est",
            "town/village": "Botley Road",
            "googleplaceids": [],
            "stopcodes": ["69323465", "69323467"],
            "position": {
                "latitude": 51.753304,
                "longitude": -1.29202
            },
            "services": ["X30", "31"]
        },
        {
            "id": 129,        
            "name": "Seacourt P&R Entry",
            "town/village": "Botley Road",
            "googleplaceids": [],
            "stopcodes": ["69323453", "69323454"],
            "position": {
                "latitude": 51.753091,
                "longitude": -1.28864
            },
            "services": ["X30", "31"]
        },
        {
            "id": 130,        
            "name": "Lamarsh Road",
            "town/village": "Botley Road",
            "googleplaceids": [],
            "stopcodes": ["69323463", "69323464"],
            "position": {
                "latitude": 51.752749,
                "longitude": -1.284124
            },
            "services": ["X30", "31"]
        },
        {
            "id": 131,        
            "name": "Binsey Lane",
            "town/village": "Botley Road",
            "googleplaceids": [],
            "stopcodes": ["69323428", "69323457"],
            "position": {
                "latitude": 51.75246,
                "longitude": -1.280159
            },
            "services": ["X30", "31"]
        },
        {
            "id": 132,        
            "name": "Osney Island",
            "town/village": "Botley Road",
            "googleplaceids": [],
            "stopcodes": ["69323459", "69323462"],
            "position": {
                "latitude": 51.752477,
                "longitude": -1.274146
            },
            "services": ["X30", "31"]
        },
        {
            "id": 133,        
            "name": "Police Station Stop P1",
            "town/village": "Oxford City Centre",
            "googleplaceids": [],
            "stopcodes": ["69345726"],
            "position": {
                "latitude": 51.74811,
                "longitude": -1.256363
            },
            "services": ["X30", "31"]
        },
        {
            "id": 134,        
            "name": "Police Station Stop P2",
            "town/village": "Oxford City Centre",
            "googleplaceids": [],
            "stopcodes": ["69345652"],
            "position": {
                "latitude": 51.747884,
                "longitude": -1.256604
            },
            "services": ["X30", "31"]
        },
        {
            "id": 135,        
            "name": "Castle Street Stop E1",
            "town/village": "Oxford City Centre",
            "googleplaceids": [],
            "stopcodes": ["69326548"],
            "position": {
                "latitude": 51.751115,
                "longitude": -1.261534
            },
            "services": ["X30", "31"]
        },
        {
            "id": 136,        
            "name": "Castle Street Stop E2",
            "town/village": "Oxford City Centre",
            "googleplaceids": [],
            "stopcodes": ["69326547"],
            "position": {
                "latitude": 51.751387,
                "longitude": -1.261191
            },
            "services": ["X30", "31"]
        },
        {
            "id": 137,        
            "name": "Castle Street Stop E3",
            "town/village": "Oxford City Centre",
            "googleplaceids": [],
            "stopcodes": ["69326526"],
            "position": {
                "latitude": 51.751587,
                "longitude": -1.26096
            },
            "services": ["8"]
        },
        {
            "id": 138,        
            "name": "Castle Street Stop M1",
            "town/village": "Oxford City Centre",
            "googleplaceids": [],
            "stopcodes": ["69326545"],
            "position": {
                "latitude": 51.751104,
                "longitude": -1.261242
            },
            "services": ["4A", "5", "13", "4"]
        },
        {
            "id": 139,        
            "name": "Castle Street Stop M2",
            "town/village": "Oxford City Centre",
            "googleplaceids": [],
            "stopcodes": ["69347482"],
            "position": {
                "latitude": 51.750883,
                "longitude": -1.261539
            },
            "services": []
        },
        {
            "id": 140,        
            "name": "St Aldates Stop G1",
            "town/village": "Oxford City Centre",
            "googleplaceids": [],
            "stopcodes": ["69326479"],
            "position": {
                "latitude": 51.750373,
                "longitude": -1.256966
            },
            "services": ["4", "4A"]
        },
        {
            "id": 141,        
            "name": "St Aldates Stop G2",
            "town/village": "Oxford City Centre",
            "googleplaceids": [],
            "stopcodes": ["69326478"],
            "position": {
                "latitude": 51.750823,
                "longitude": -1.257135
            },
            "services": ["13", "X13"]
        },
        {
            "id": 142,        
            "name": "St Aldates Stop G3",
            "town/village": "Oxford City Centre",
            "googleplaceids": [],
            "stopcodes": ["69326476"],
            "position": {
                "latitude": 51.751162,
                "longitude": -1.257334
            },
            "services": ["10", "12C", "U5"]
        },
        {
            "id": 143,        
            "name": "St Aldates Stop G4",
            "town/village": "Oxford City Centre",
            "googleplaceids": [],
            "stopcodes": ["69326475"],
            "position": {
                "latitude": 51.751457,
                "longitude": -1.257489
            },
            "services": ["1", "5"]
        },
        {
            "id": 144,        
            "name": "St Aldates Stop G5",
            "town/village": "Oxford City Centre",
            "googleplaceids": [],
            "stopcodes": ["69326474"],
            "position": {
                "latitude": 51.75165,
                "longitude": -1.25757
            },
            "services": []
        },
        {
            "id": 145,        
            "name": "St Aldates Stop H1",
            "town/village": "Oxford City Centre",
            "googleplaceids": [],
            "stopcodes": ["69326473"],
            "position": {
                "latitude": 51.750874,
                "longitude": -1.257001
            },
            "services": ["X13", "X3"]
        },
        {
            "id": 146,        
            "name": "St Aldates Stop H2",
            "town/village": "Oxford City Centre",
            "googleplaceids": [],
            "stopcodes": ["69326472"],
            "position": {
                "latitude": 51.750748,
                "longitude": -1.256923
            },
            "services": ["300"]
        },
        {
            "id": 147,        
            "name": "St Aldates Stop H3",
            "town/village": "Oxford City Centre",
            "googleplaceids": [],
            "stopcodes": ["69326469"],
            "position": {
                "latitude": 51.750602,
                "longitude": -1.25688
            },
            "services": ["35"]
        },
        {
            "id": 148,        
            "name": "St Aldates Stop H4",
            "town/village": "Oxford City Centre",
            "googleplaceids": [],
            "stopcodes": ["69326468"],
            "position": {
                "latitude": 51.750477,
                "longitude": -1.256838
            },
            "services": ["35"]
        },
        {
            "id": 149,        
            "name": "St Aldates Stop H5",
            "town/village": "Oxford City Centre",
            "googleplaceids": [],
            "stopcodes": ["69326543"],
            "position": {
                "latitude": 51.75028,
                "longitude": -1.256768
            },
            "services": ["OXF", "X90", "TUBE", "X2"]
        },
        {
            "id": 150,        
            "name": "Sugworth Lane",
            "town/village": "Bagley Wood",
            "googleplaceids": [],
            "stopcodes": ["69323957", "69342356"],
            "position": {
                "latitude": 51.703138,
                "longitude": -1.266421
            },
            "services": ["31"]
        },
        {
            "id": 151,        
            "name": "Post Office",
            "town/village": "Marcham",
            "googleplaceids": [],
            "stopcodes": ["69328384", "69328385"],
            "position": {
                "latitude": 51.667442,
                "longitude": -1.344146
            },
            "services": ["31"]
        },
        {
            "id": 152,        
            "name": "Duffield Place",
            "town/village": "Marcham",
            "googleplaceids": [],
            "stopcodes": ["69328386", "69328387"],
            "position": {
                "latitude": 51.670389,
                "longitude": -1.344135
            },
            "services": ["31"]
        },
        {
            "id": 153,        
            "name": "Longfields",
            "town/village": "Marcham",
            "googleplaceids": [],
            "stopcodes": ["69328389", "69328392"],
            "position": {
                "latitude": 51.670662,
                "longitude": -1.340611
            },
            "services": ["31"]
        },
        {
            "id": 154,        
            "name": "Morland Road",
            "town/village": "Marcham",
            "googleplaceids": [],
            "stopcodes": ["69328393", "69324258"],
            "position": {
                "latitude": 51.667435,
                "longitude": -1.337473
            },
            "services": ["31"]
        },
        {
            "id": 155,        
            "name": "War Memorial",
            "town/village": "Marcham",
            "googleplaceids": [],
            "stopcodes": ["69329329", "69328943"],
            "position": {
                "latitude": 51.666414,
                "longitude": -1.344849
            },
            "services": ["31"]
        },
        {
            "id": 156,        
            "name": "Fairacres",
            "town/village": "Abingdon",
            "googleplaceids": [],
            "stopcodes": ["69328394", "69328329"],
            "position": {
                "latitude": 51.668546,
                "longitude": -1.307834
            },
            "services": ["31"]
        },
        {
            "id": 157,        
            "name": "Community Hospital",
            "town/village": "Abingdon",
            "googleplaceids": [],
            "stopcodes": ["69326385", "69329326"],
            "position": {
                "latitude": 51.669378,
                "longitude": -1.300544
            },
            "services": ["31"]
        },
        {
            "id": 158,        
            "name": "Victoria Road",
            "town/village": "Abingdon",
            "googleplaceids": [],
            "stopcodes": ["69328259", "69328262"],
            "position": {
                "latitude": 51.669275,
                "longitude": -1.292991
            },
            "services": ["31"]
        },
        {
            "id": 159,        
            "name": "Conduit Road",
            "town/village": "Abingdon",
            "googleplaceids": [],
            "stopcodes": ["69328263", "69328264"],
            "position": {
                "latitude": 51.669588,
                "longitude": -1.288565
            },
            "services": ["31"]
        },
        {
            "id": 160,        
            "name": "Coxeters",
            "town/village": "Abingdon",
            "googleplaceids": [],
            "stopcodes": ["69328435"],
            "position": {
                "latitude": 51.670043,
                "longitude": -1.286023
            },
            "services": ["31"]
        },
        {
            "id": 161,        
            "name": "Stratton Way Stop A1",
            "town/village": "Abingdon",
            "googleplaceids": [],
            "stopcodes": ["69326784"],
            "position": {
                "latitude": 51.671404,
                "longitude": -1.28488
            },
            "services": ["31"]
        },
        {
            "id": 162,        
            "name": "Stratton Way Stop A2",
            "town/village": "Abingdon",
            "googleplaceids": [],
            "stopcodes": ["69346289"],
            "position": {
                "latitude": 51.671224,
                "longitude": -1.285089
            },
            "services": ["X2", "X3", "X13"]
        },
        {
            "id": 163,        
            "name": "Stratton Way Stop A3",
            "town/village": "Abingdon",
            "googleplaceids": [],
            "stopcodes": ["69346292"],
            "position": {
                "latitude": 51.671005,
                "longitude": -1.285272
            },
            "services": ["4", "35"]
        },
        {
            "id": 164,        
            "name": "Stratton Way Stop A4",
            "town/village": "Abingdon",
            "googleplaceids": [],
            "stopcodes": ["69346293"],
            "position": {
                "latitude": 51.671038,
                "longitude": -1.284955
            },
            "services": ["31"]
        },
        {
            "id": 165,        
            "name": "Vineyard",
            "town/village": "Abingdon",
            "googleplaceids": [],
            "stopcodes": ["69345469", "69345473"],
            "position": {
                "latitude": 51.673374,
                "longitude": -1.279778
            },
            "services": ["31", "X1", "X2", "X3", "X13"]
        },
        {
            "id": 166,        
            "name": "Our Lady's Oxford Road",
            "town/village": "Abingdon",
            "googleplaceids": [],
            "stopcodes": ["69323936", "69323938"],
            "position": {
                "latitude": 51.675077,
                "longitude": -1.277799
            },
            "services": ["31", "X1", "X2", "X3", "X13"]
        },
        {
            "id": 167,        
            "name": "Our Lady's Radley Road",
            "town/village": "Abingdon",
            "googleplaceids": [],
            "stopcodes": ["69323549", "69323548"],
            "position": {
                "latitude": 51.674468,
                "longitude": -1.277279
            },
            "services": ["35"]
        },
        {
            "id": 168,        
            "name": "The Ox",
            "town/village": "Abingdon",
            "googleplaceids": [],
            "stopcodes": ["69323939", "69323937"],
            "position": {
                "latitude": 51.677598,
                "longitude": -1.2756
            },
            "services": ["31"]
        },
        {
            "id": 169,        
            "name": "Boundary House",
            "town/village": "Abingdon",
            "googleplaceids": [],
            "stopcodes": ["69324684", "69324683"],
            "position": {
                "latitude": 51.682734,
                "longitude": -1.273604
            },
            "services": ["31"]
        },
        {
            "id": 170,        
            "name": "South Avenue",
            "town/village": "Abingdon",
            "googleplaceids": [],
            "stopcodes": ["69324636", "69324635"],
            "position": {
                "latitude": 51.685568,
                "longitude": -1.272655
            },
            "services": ["31"]
        },
        {
            "id": 171,        
            "name": "Peachcroft Roundabout",
            "town/village": "Abingdon",
            "googleplaceids": [],
            "stopcodes": ["69325752", "69325749"],
            "position": {
                "latitude": 51.689133,
                "longitude": -1.270997
            },
            "services": ["X1", "X2", "X3", "X13", "31"]
        },
        {
            "id": 172,        
            "name": "Lodge Hill",
            "town/village": "Abingdon",
            "googleplaceids": [],
            "stopcodes": ["69324257", "69324256"],
            "position": {
                "latitude": 51.695753,
                "longitude": -1.26839
            },
            "services": ["X1", "X2", "X3", "X13", "31"]
        },
        {
            "id": 173,        
            "name": "George Street Stop A2",
            "town/village": "Oxford City Centre",
            "googleplaceids": [],
            "stopcodes": ["69327527"],
            "position": {
                "latitude": 51.753708,
                "longitude": -1.260078
            },
            "services": ["300"]
        },
        {
            "id": 174,        
            "name": "George Street Stop B1",
            "town/village": "Oxford City Centre",
            "googleplaceids": [],
            "stopcodes": ["69327545"],
            "position": {
                "latitude": 51.753521,
                "longitude": -1.26221
            },
            "services": ["300", "S1", "14"]
        },
        {
            "id": 175,        
            "name": "Magdalen Street Stop C1",
            "town/village": "Oxford City Centre",
            "googleplaceids": [],
            "stopcodes": ["69326546"],
            "position": {
                "latitude": 51.75433,
                "longitude": -1.259066
            },
            "services": []
        },
        {
            "id": 176,        
            "name": "Magdalen Street Stop C3",
            "town/village": "Oxford City Centre",
            "googleplaceids": [],
            "stopcodes": ["69326572"],
            "position": {
                "latitude": 51.754807,
                "longitude": -1.259234
            },
            "services": []
        },
        {
            "id": 177,        
            "name": "St Giles",
            "town/village": "Oxford City Centre",
            "googleplaceids": [],
            "stopcodes": ["69327498"],
            "position": {
                "latitude": 51.755754,
                "longitude": -1.259592
            },
            "services": []
        },
        {
            "id": 178,        
            "name": "Carfax Stop i1",
            "town/village": "Oxford City Centre",
            "googleplaceids": [],
            "stopcodes": ["69326483"],
            "position": {
                "latitude": 51.752188,
                "longitude": -1.25559
            },
            "services": ["4A", "4B", "U1", "U5", "400"]
        },
        {
            "id": 179,        
            "name": "Carfax Stop i2",
            "town/village": "Oxford City Centre",
            "googleplaceids": [],
            "stopcodes": ["69326482"],
            "position": {
                "latitude": 51.752088,
                "longitude": -1.256497
            },
            "services": ["3", "5", "13", "280", "X13"]
        },
        {
            "id": 180,        
            "name": "Turl Street Stop L1",
            "town/village": "Oxford City Centre",
            "googleplaceids": [],
            "stopcodes": ["69342763"],
            "position": {
                "latitude": 51.752347,
                "longitude": -1.255344
            },
            "services": ["U1", "280"]
        },
        {
            "id": 181,        
            "name": "Queens Lane Stop J1",
            "town/village": "Oxford City Centre",
            "googleplaceids": [],
            "stopcodes": ["69345693"],
            "position": {
                "latitude": 51.752593,
                "longitude": -1.2508
            },
            "services": ["8", "9", "X90", "TUBE"]
        },
        {
            "id": 182,        
            "name": "Queens Lane Stop J2",
            "town/village": "Oxford City Centre",
            "googleplaceids": [],
            "stopcodes": ["69345729"],
            "position": {
                "latitude": 51.752643,
                "longitude": -1.251315
            },
            "services": ["1", "10", "12"]
        },
        {
            "id": 183,        
            "name": "Queens Lane Stop J3",
            "town/village": "Oxford City Centre",
            "googleplaceids": [],
            "stopcodes": ["69345658"],
            "position": {
                "latitude": 51.752663,
                "longitude": -1.251503
            },
            "services": ["3", "4A", "5", "280", "U1", "X13", "400"]
        },
        {
            "id": 184,        
            "name": "Queens Lane Stop K1",
            "town/village": "Oxford City Centre",
            "googleplaceids": [],
            "stopcodes": ["69345686"],
            "position": {
                "latitude": 51.752779,
                "longitude": -1.251492
            },
            "services": ["1", "5", "10"]
        },
        {
            "id": 185,        
            "name": "Queens Lane Stop K2",
            "town/village": "Oxford City Centre",
            "googleplaceids": [],
            "stopcodes": ["69345687"],
            "position": {
                "latitude": 51.752772,
                "longitude": -1.251299
            },
            "services": ["3", "12", "T1"]
        },
        {
            "id": 186,        
            "name": "Queens Lane Stop K3",
            "town/village": "Oxford City Centre",
            "googleplaceids": [],
            "stopcodes": ["69343965"],
            "position": {
                "latitude": 51.752752,
                "longitude": -1.251165
            },
            "services": ["4", "4A", "4B", "400", "X13", "13"]
        },
        {
            "id": 187,        
            "name": "Queens Lane Stop K4",
            "town/village": "Oxford City Centre",
            "googleplaceids": [],
            "stopcodes": ["69345692"],
            "position": {
                "latitude": 51.752749,
                "longitude": -1.250864
            },
            "services": ["8", "U1", "U5", "TUBE"]
        },
        {
            "id": 188,        
            "name": "Queens Lane Stop K5",
            "town/village": "Oxford City Centre",
            "googleplaceids": [],
            "stopcodes": ["69345728"],
            "position": {
                "latitude": 51.752716,
                "longitude": -1.250639
            },
            "services": ["280", "LHR", "LGW", "X90"]
        },
        {
            "id": 189,        
            "name": "Gloucester Green Bus Station Bay 3",
            "town/village": "Oxford City Centre",
            "googleplaceids": [],
            "stopcodes": ["69326524"],
            "position": {
                "latitude": 51.753829,
                "longitude": -1.26249
            },
            "services": ["TUBE"]
        },
        {
            "id": 190,        
            "name": "Gloucester Green Bus Station Bay 5",
            "town/village": "Oxford City Centre",
            "googleplaceids": [],
            "stopcodes": ["69326498"],
            "position": {
                "latitude": 51.754042,
                "longitude": -1.262497
            },
            "services": ["X90"]
        },
        {
            "id": 191,        
            "name": "Gloucester Green Bus Station Bay 6",
            "town/village": "Oxford City Centre",
            "googleplaceids": [],
            "stopcodes": ["69326497"],
            "position": {
                "latitude": 51.754042,
                "longitude": -1.262497
            },
            "services": []
        },
        {
            "id": 192,        
            "name": "Gloucester Green Bus Station Bay 7",
            "town/village": "Oxford City Centre",
            "googleplaceids": [],
            "stopcodes": ["69326496"],
            "position": {
                "latitude": 51.754042,
                "longitude": -1.262497
            },
            "services": []
        },
        {
            "id": 193,        
            "name": "Gloucester Green Bus Station Bay 11",
            "town/village": "Oxford City Centre",
            "googleplaceids": [],
            "stopcodes": ["69326492"],
            "position": {
                "latitude": 51.754149,
                "longitude": -1.262455
            },
            "services": ["X5"]
        },
        {
            "id": 194,        
            "name": "Speedwell Street Stop S2",
            "town/village": "Oxford City Centre",
            "googleplaceids": [],
            "stopcodes": ["69345627"],
            "position": {
                "latitude": 51.748452,
                "longitude": -1.258149
            },
            "services": ["TUBE"]
        },
        {
            "id": 195,        
            "name": "Speedwell Street Stop S1",
            "town/village": "Oxford City Centre",
            "googleplaceids": [],
            "stopcodes": ["69345486"],
            "position": {
                "latitude": 51.748448,
                "longitude": -1.257342
            },
            "services": ["3", "5", "8", "13", "4B", "400", "U1"]
        },
        {
            "id": 196,        
            "name": "St Clements Street Stop A",
            "town/village": "Oxford City Centre",
            "googleplaceids": [],
            "stopcodes": ["69323265"],
            "position": {
                "latitude": 51.750477,
                "longitude": -1.240806
            },
            "services": ["8", "U1", "400", "280", "X90", "TUBE"]
        },
        {
            "id": 197,        
            "name": "St Clements Street Stop C",
            "town/village": "Oxford City Centre",
            "googleplaceids": [],
            "stopcodes": ["69323289"],
            "position": {
                "latitude": 51.750159,
                "longitude": -1.242072
            },
            "services": ["13", "X13", "400", "X90", "U1", "8", "TUBE", "U1", "4", "4A", "OXF", "280"]
        },
        {
            "id": 198,        
            "name": "St Clements Street Stop B",
            "town/village": "Oxford City Centre",
            "googleplaceids": [],
            "stopcodes": ["69325658"],
            "position": {
                "latitude": 51.750159,
                "longitude": -1.242072
            },
            "services": ["X13", "4A", "LGW", "13", "S5", "4A", "4B", "4"]
        },
        {
            "id": 199,        
            "name": "Brookes University Stop B3",
            "town/village": "Headington",
            "googleplaceids": [],
            "stopcodes": ["69347427"],
            "position": {
                "latitude": 51.756023,
                "longitude": -1.224761
            },
            "services": ["TUBE", "X90", "LGW"]
        },
        {
            "id": 200,        
            "name": "Headington Shops Stop HS5",
            "town/village": "Headington",
            "googleplaceids": [],
            "stopcodes": ["69347625"],
            "position": {
                "latitude": 51.760539,
                "longitude": -1.209816
            },
            "services": ["TUBE", "X90", "LGW"]
        },
        {
            "id": 201,        
            "name": "Brookes University Stop B2",
            "town/village": "Headington",
            "googleplaceids": [],
            "stopcodes": ["69325678"],
            "position": {
                "latitude": 51.755881,
                "longitude": -1.225217
            },
            "services": ["8", "U1", "280"]
        },
        {
            "id": 202,        
            "name": "Brookes University Stop B4",
            "town/village": "Headington",
            "googleplaceids": [],
            "stopcodes": ["69347426"],
            "position": {
                "latitude": 51.755359,
                "longitude": -1.226799
            },
            "services": ["X90", "TUBE", "OXF"]
        },
        {
            "id": 203,        
            "name": "Brookes University Stop B5",
            "town/village": "Headington",
            "googleplaceids": [],
            "stopcodes": ["69325679"],
            "position": {
                "latitude": 51.755469,
                "longitude": -1.226215
            },
            "services": ["8", "X13", "U1", "U5"]
        },
        {
            "id": 204,        
            "name": "Headington Shops Stop HS1",
            "town/village": "Headington",
            "googleplaceids": [],
            "stopcodes": ["69342583"],
            "position": {
                "latitude": 51.759583,
                "longitude": -1.213163
            },
            "services": ["400", "10"]
        },
        {
            "id": 205,        
            "name": "Headington Shops Stop HS2",
            "town/village": "Headington",
            "googleplaceids": [],
            "stopcodes": ["69325689"],
            "position": {
                "latitude": 51.759905,
                "longitude": -1.211661
            },
            "services": ["U1", "400", "700", "8", "10"]
        },
        {
            "id": 206,        
            "name": "Headington Shops Stop HS3",
            "town/village": "Headington",
            "googleplaceids": [],
            "stopcodes": ["69325452"],
            "position": {
                "latitude": 51.759261,
                "longitude": -1.210266
            },
            "services": ["900", "10"]
        },
        {
            "id": 207,        
            "name": "Headington Shops Stop HS4",
            "town/village": "Headington",
            "googleplaceids": [],
            "stopcodes": ["69325452"],
            "position": {
                "latitude": 51.760267,
                "longitude": -1.210304
            },
            "services": ["X90", "OXF", "TUBE"]
        },
        {
            "id": 208,        
            "name": "Headington Shops Stop HS6",
            "town/village": "Headington",
            "googleplaceids": [],
            "stopcodes": ["69325692"],
            "position": {
                "latitude": 51.760459,
                "longitude": -1.2101
            },
            "services": ["900", "8", "U1", "280", "800"]
        },
        {
            "id": 209,        
            "name": "Green Road Roundabout",
            "town/village": "Headington",
            "googleplaceids": [],
            "stopcodes": ["69325687", "69325686"],
            "position": {
                "latitude": 51.762485,
                "longitude": -1.199731
            },
            "services": ["TUBE"]
        },
        {
            "id": 210,        
            "name": "Thornhill P&R Bay A",
            "town/village": "Thornhill",
            "googleplaceids": [],
            "stopcodes": ["69326542"],
            "position": {
                "latitude": 51.76181,
                "longitude": -1.18105
            },
            "services": ["TUBE", "X90"]
        },
        {
            "id": 211,        
            "name": "Thornhill P&R Bay B",
            "town/village": "Thornhill",
            "googleplaceids": [],
            "stopcodes": ["69347252"],
            "position": {
                "latitude": 51.76181,
                "longitude": -1.18105
            },
            "services": ["400"]
        },
        {
            "id": 212,        
            "name": "Thornhill P&R Bay C",
            "town/village": "Thornhill",
            "googleplaceids": [],
            "stopcodes": ["69347253"],
            "position": {
                "latitude": 51.76181,
                "longitude": -1.18105
            },
            "services": ["X90", "OXF", "TUBE"]
        },
        {
            "id": 213,        
            "name": "Thornhill P&R Bay D",
            "town/village": "Thornhill",
            "googleplaceids": [],
            "stopcodes": ["69347254"],
            "position": {
                "latitude": 51.76181,
                "longitude": -1.18105
            },
            "services": ["LHR"]
        },
        {
            "id": 214,        
            "name": "Lewknor Turn Stop B",
            "town/village": "Lewknor",
            "googleplaceids": [],
            "stopcodes": ["69345498"],
            "position": {
                "latitude": 51.673279,
                "longitude": -0.958721
            },
            "services": ["TUBE"]
        },
        {
            "id": 215,        
            "name": "Hillingdon",
            "town/village": "North Hillingdon",
            "googleplaceids": [],
            "stopcodes": ["27248282"],
            "position": {
                "latitude": 51.553577,
                "longitude": -0.448326
            },
            "services": ["TUBE"]
        },
        {
            "id": 216,        
            "name": "Royal Crescent Stop HJ",
            "town/village": "Notting Hill",
            "googleplaceids": [],
            "stopcodes": ["27245467"],
            "position": {
                "latitude": 51.505257,
                "longitude": -0.214101
            },
            "services": ["TUBE"]
        },
        {
            "id": 217,        
            "name": "Palace Gardens Terrace",
            "town/village": "Kensington",
            "googleplaceids": [],
            "stopcodes": ["27245354"],
            "position": {
                "latitude": 51.509707,
                "longitude": -0.193366
            },
            "services": ["TUBE"]
        },
        {
            "id": 218,        
            "name": "Marble Arch Stop S",
            "town/village": "Mayfair",
            "googleplaceids": [],
            "stopcodes": ["27245357"],
            "position": {
                "latitude": 51.512089,
                "longitude": -0.157512
            },
            "services": ["TUBE"]
        },
        {
            "id": 219,        
            "name": "Bressenden Place",
            "town/village": "Belgravia",
            "googleplaceids": [],
            "stopcodes": ["27245423"],
            "position": {
                "latitude": 51.497743,
                "longitude": -0.143901
            },
            "services": ["TUBE"]
        },
        {
            "id": 220,        
            "name": "Green Line Coach Station",
            "town/village": "Victoria",
            "googleplaceids": [],
            "stopcodes": ["27245469"],
            "position": {
                "latitude": 51.492824,
                "longitude": -0.147521
            },
            "services": ["TUBE"]
        },
        {
            "id": 221,        
            "name": "Victoria Stop 10A",
            "town/village": "Victoria",
            "googleplaceids": [],
            "stopcodes": ["27245473"],
            "position": {
                "latitude": 51.49675,
                "longitude": -0.146172
            },
            "services": ["TUBE"]
        },
        {
            "id": 222,        
            "name": "Marble Arch Stop 14",
            "town/village": "Mayfair",
            "googleplaceids": [],
            "stopcodes": ["27247584"],
            "position": {
                "latitude": 51.51189,
                "longitude": -0.158515
            },
            "services": ["TUBE"]
        },
        {
            "id": 223,        
            "name": "Notting Hill Gate Stop N",
            "town/village": "Notting Hill",
            "googleplaceids": [],
            "stopcodes": ["27245367"],
            "position": {
                "latitude": 51.509602,
                "longitude": -0.192963
            },
            "services": ["TUBE"]
        },
        {
            "id": 224,        
            "name": "Royal Crescent Stop HD",
            "town/village": "Notting Hill",
            "googleplaceids": [],
            "stopcodes": ["27245482"],
            "position": {
                "latitude": 51.505104,
                "longitude": -0.214165
            },
            "services": ["TUBE"]
        },
        {
            "id": 225,        
            "name": "Hillingdon Circus",
            "town/village": "North Hillingdon",
            "googleplaceids": [],
            "stopcodes": ["27245426"],
            "position": {
                "latitude": 51.551696,
                "longitude": -0.447564
            },
            "services": ["TUBE"]
        },
        {
            "id": 226,        
            "name": "Lewknor Turn Stop A",
            "town/village": "Lewknor",
            "googleplaceids": [],
            "stopcodes": ["69345497"],
            "position": {
                "latitude": 51.671494,
                "longitude": -0.963462
            },
            "services": ["TUBE"]
        },
        {
            "id": 227,        
            "name": "Gladstone Road",
            "town/village": "Headington",
            "googleplaceids": [],
            "stopcodes": ["69325627", "69325675"],
            "position": {
                "latitude": 51.762126,
                "longitude": -1.202241
            },
            "services": ["TUBE"]
        },
        {
            "id": 228,        
            "name": "The Oxford Arms",
            "town/village": "Kirtlington",
            "googleplaceids": [],
            "stopcodes": ["69327657", "69327656"],
            "position": {
                "latitude": 51.872195,
                "longitude": -1.276946
            },
            "services": []
        },
        {
            "id": 229,        
            "name": "Chesterton Turn North",
            "town/village": "A41",
            "googleplaceids": [],
            "stopcodes": ["69329494"],
            "position": {
                "latitude": 51.887566,
                "longitude": -1.168115
            },
            "services": ["S5"]
        },
        {
            "id": 230,        
            "name": "Chesterton Turn South",
            "town/village": "A41",
            "googleplaceids": [],
            "stopcodes": ["69329493"],
            "position": {
                "latitude": 51.883686,
                "longitude": -1.172473
            },
            "services": ["S5"]
        },
        {
            "id": 231,        
            "name": "Red Lion",
            "town/village": "Wendlebury",
            "googleplaceids": [],
            "stopcodes": ["69326974", "69326973"],
            "position": {
                "latitude": 51.873083,
                "longitude": -1.185697
            },
            "services": ["S5"]
        },
        {
            "id": 232,        
            "name": "Wendlebury Turn",
            "town/village": "A41",
            "googleplaceids": [],
            "stopcodes": ["69329489", "69329492"],
            "position": {
                "latitude": 51.873404,
                "longitude": -1.190815
            },
            "services": ["S5"]
        }
    ],
    "services": [
        {
            "name": "S3",
            "operator": "Stagecoach",
            "operator_code": "SOX"
        }
    ],
    "operators": [
        {
            "operator_code": "SOX",
            "logo": "stagecoach.png"
        }
    ]
}
